opensesame_plugins/screenshot/__init__.py
opensesame_plugins/screenshot/screenshot/__init__.py
opensesame_plugins/screenshot/screenshot/screenshot.png
opensesame_plugins/screenshot/screenshot/screenshot.py
opensesame_plugins/screenshot/screenshot/screenshot_large.png
opensesame_plugin_screenshot-0.6.1.dist-info/COPYING
opensesame_plugin_screenshot-0.6.1.dist-info/LICENSE.md
opensesame_plugin_screenshot-0.6.1.dist-info/METADATA
opensesame_plugin_screenshot-0.6.1.dist-info/WHEEL
opensesame_plugin_screenshot-0.6.1.dist-info/RECORD
