Metadata-Version: 2.3
Name: opensesame-plugin-screenshot
Version: 0.6.1
Summary: An OpenSesame Plugin for saving screenshots of stimuli and other screens within an experiment.
License: LICENSE.md
Author: Bob Rosbag
Author-email: debian@bobrosbag.nl
Requires-Python: >=3.7
Classifier: License :: Other/Proprietary License
Classifier: Programming Language :: Python :: 3
Classifier: Programming Language :: Python :: 3.7
Classifier: Programming Language :: Python :: 3.8
Classifier: Programming Language :: Python :: 3.9
Classifier: Programming Language :: Python :: 3.10
Classifier: Programming Language :: Python :: 3.11
Classifier: Programming Language :: Python :: 3.12
Classifier: Programming Language :: Python :: 3.13
Requires-Dist: screeninfo
Project-URL: Homepage, https://github.com/dev-jam/opensesame-plugin-screenshot
Project-URL: Repository, https://github.com/dev-jam/opensesame-plugin-screenshot
